spexygen.py
spexygen-2.3.0.dist-info/LICENSE
spexygen-2.3.0.dist-info/METADATA
spexygen-2.3.0.dist-info/WHEEL
spexygen-2.3.0.dist-info/entry_points.txt
spexygen-2.3.0.dist-info/top_level.txt
spexygen-2.3.0.dist-info/RECORD
