Metadata-Version: 2.1
Name: spexygen
Version: 2.3.0
Summary: Traceable specifications based on doxygen
Home-page: https://github.com/QuantumLeaps/spexygen
Author: Quantum Leaps
Author-email: info@state-machine.com
License: MIT
Platform: any
Classifier: Development Status :: 5 - Production/Stable
Classifier: Intended Audience :: Developers
Classifier: Topic :: Software Development :: Documentation
Classifier: License :: OSI Approved :: MIT License
Classifier: Operating System :: Microsoft :: Windows
Classifier: Operating System :: POSIX :: Linux
Classifier: Operating System :: MacOS :: MacOS X
Classifier: Programming Language :: Python
Classifier: Programming Language :: Python :: 3
License-File: LICENSE
